mind/__init__.py
mind/cli.py
mind/config.py
mind/context.py
mind/detection.py
mind/mascot.py
mind/parser.py
mind/self_improve.py
mind/storage.py
mind/templates.py
mind/mcp/__init__.py
mind/mcp/server.py
mind_memory-2.1.0.dist-info/METADATA
mind_memory-2.1.0.dist-info/WHEEL
mind_memory-2.1.0.dist-info/entry_points.txt
mind_memory-2.1.0.dist-info/licenses/LICENSE
mind_memory-2.1.0.dist-info/RECORD
