Metadata-Version: 2.4
Name: mind-memory
Version: 2.1.0
Summary: File-based memory system for AI coding assistants
License-File: LICENSE
Requires-Python: >=3.11
Requires-Dist: click>=8.1.0
Requires-Dist: mcp>=1.0.0
Requires-Dist: watchfiles>=0.21.0
